ethdasm/__init__.py
ethdasm/contract.py
ethdasm/contract_test.py
ethdasm/opcodes.py
ethdasm/opcodes_test.py
ethdasm/parse.py
ethdasm-0.1.0.dist-info/METADATA
ethdasm-0.1.0.dist-info/WHEEL
ethdasm-0.1.0.dist-info/top_level.txt
ethdasm-0.1.0.dist-info/RECORD
