Metadata-Version: 2.1
Name: ethdasm
Version: 0.1.0
Summary: Tool for auditing Ethereum contracts
Home-page: https://github.com/meyer9/ethdasm
Author: meyer9
Author-email: UNKNOWN
License: UNKNOWN
Platform: UNKNOWN
Classifier: Development Status :: 3 - Alpha
Classifier: License :: OSI Approved :: MIT License
Classifier: Programming Language :: Python :: 3
Classifier: Programming Language :: Python :: 3.6
Classifier: Programming Language :: Python :: 3.7
Classifier: Programming Language :: Python :: 3.8
Classifier: Programming Language :: Python :: 3.9
